space2stats_client/__init__.py
space2stats_client/client.py
space2stats_client/utils.py
space2stats_client/widgets/__init__.py
space2stats_client/widgets/aoi_selector.py
space2stats_client/widgets/cross_section_field_selector.py
space2stats_client/widgets/time_series_field_selector.py
space2stats_client-1.4.1.dist-info/licenses/LICENSE
space2stats_client-1.4.1.dist-info/METADATA
space2stats_client-1.4.1.dist-info/WHEEL
space2stats_client-1.4.1.dist-info/top_level.txt
space2stats_client-1.4.1.dist-info/RECORD
