Metadata-Version: 2.4
Name: space2stats-client
Version: 1.4.1
Summary: A Python client for accessing sub-national variation data through the Space2Stats API
Author-email: Gabe Levin <glevin@worldbank.org>, Andres Chamorro <achamorroelizond@worldbank.org>
License: World Bank Master Community License Agreement
Project-URL: Homepage, https://github.com/worldbank/DECAT_Space2Stats.git
Project-URL: Documentation, https://worldbank.github.io/DECAT_Space2Stats/
Project-URL: Repository, https://github.com/worldbank/DECAT_Space2Stats.git
Keywords: gis,spatial,statistics,world bank,development
Classifier: Development Status :: 4 - Beta
Classifier: Intended Audience :: Science/Research
Classifier: Programming Language :: Python :: 3.9
Classifier: Programming Language :: Python :: 3.10
Classifier: Programming Language :: Python :: 3.11
Classifier: Programming Language :: Python :: 3.12
Classifier: Programming Language :: Python :: 3.13
Classifier: Operating System :: OS Independent
Classifier: Topic :: Scientific/Engineering :: GIS
Requires-Python: <=3.13,>=3.9
License-File: LICENSE
Requires-Dist: pandas>=1.5.0
Requires-Dist: geopandas>=0.12.0
Requires-Dist: requests>=2.25.0
Requires-Dist: pystac>=1.0.0
Provides-Extra: widgets
Requires-Dist: ipywidgets>=8.0.0; extra == "widgets"
Requires-Dist: ipyleaflet>=0.17.0; extra == "widgets"
Requires-Dist: IPython>=7.0.0; extra == "widgets"
Dynamic: license-file
